{
  "north": {
    "1": "Protect sensitive plants from frost. Plan your spring garden layout.",
    "2": "Start seeds indoors for tomatoes, peppers. Prune dormant trees and shrubs.",
    "3": "Plant cool-season crops: lettuce, spinach, peas, radishes. Prepare beds.",
    "4": "Sow carrots, beets, direct-seed beans. Plant perennials and new shrubs.",
    "5": "Transplant seedlings outdoors after last frost. Mulch to retain moisture.",
    "6": "Harvest early crops. Water consistently — especially during heat waves.",
    "7": "Deadhead flowers regularly. Watch for pests and fungal issues in humidity.",
    "8": "Harvest peak summer vegetables. Plant fall crops (kale, broccoli, etc.).",
    "9": "Plant spring-flowering bulbs. Clean up garden debris and compost.",
    "10": "Divide overcrowded perennials. Protect tender plants before first frost.",
    "11": "Apply winter mulch. Clean and store tools. Order seeds for next year.",
    "12": "Rest and plan next year's garden. Review notes from this season."
  }
}